LICENSE.txt
README.md
pyproject.toml
ecpet/__init__.py
ecpet/__main__.py
ecpet/_version.py
ecpet/ec_config_dialog.py
ecpet/ec_config_wizard.py
ecpet/ecconfig.py
ecpet/ecdb.py
ecpet/ecdefaults.py
ecpet/ecengine.py
ecpet/ecfile.py
ecpet/eclogger.py
ecpet/ecmain.py
ecpet/ecpack.py
ecpet/ecplan.py
ecpet/ecpost.py
ecpet/ecpre.py
ecpet/ecutils.py
ecpet.egg-info/PKG-INFO
ecpet.egg-info/SOURCES.txt
ecpet.egg-info/dependency_links.txt
ecpet.egg-info/entry_points.txt
ecpet.egg-info/requires.txt
ecpet.egg-info/top_level.txt
ecpet/images/CSATSonic.png
ecpet/images/CampKrypton.png
ecpet/images/GillSolent.png
ecpet/images/KaijoTR61.png
ecpet/images/KaijoTR90.png
ecpet/images/LiCor7500.png
ecpet/images/MetekUSA1.png
ecpet/images/Open-Wire.png
ecpet/images/TCouple.png
ecpet/images/ec-pet-icon.16.png
ecpet/images/ec-pet-icon.22.png
ecpet/images/ec-pet-icon.32.png
ecpet/images/ec-pet-icon.48.png
ecpet/images/ec-pet-icon.64.png
ecpet/images/gui-image_text.png
ecpet/images/missing.png
ecpet/images/not-present.png