Metadata-Version: 2.4
Name: ecpet
Version: 2.1.0b1
Summary: A modern eddy-covariance software inspired by EC-PACK.
Author-email: Clemens Drüe <druee@uni-trier.de>
License: EUPL-1.2
Project-URL: Homepage, https://meteo.uni-trier.de/ec-pet/
Keywords: eddy-covariance,data-analysis,atmospheric
Classifier: Development Status :: 4 - Beta
Classifier: Environment :: Console
Classifier: Environment :: X11 Applications :: Qt
Classifier: Intended Audience :: Science/Research
Classifier: Operating System :: OS Independent
Classifier: Programming Language :: Python :: 3
Classifier: Programming Language :: Python :: 3.7
Classifier: Programming Language :: Python :: 3.8
Classifier: Programming Language :: Python :: 3.9
Classifier: Programming Language :: Python :: 3.10
Classifier: Programming Language :: Python :: 3.11
Classifier: Topic :: Scientific/Engineering :: Atmospheric Science
Requires-Python: >=3.7
License-File: LICENSE.txt
Requires-Dist: numpy
Requires-Dist: scipy
Requires-Dist: pandas
Requires-Dist: netCDF4
Requires-Dist: python-dateutil
Requires-Dist: requests
Requires-Dist: wxPython>=4.0
Requires-Dist: matplotlib>=3.0
Requires-Dist: Pypubsub
Requires-Dist: pillow
Dynamic: license-file
